{
	"start" : {
				"title": "Info",
				"view": "org.mgnl.nicki.vaadin.base.views.InfoView",
				"configuration" : {
					"editorGroup" : "time-administrators",
					"storeClass" : "org.mgnl.nicki.vaadin.base.views.TemplateInfo",
					"configPath" : "nicki.consulting.projects.info.path"
				}
			},
	"chapters": [
		{
			"chapter": "Administration",
			"groups" : ["time-administrators"],
			"views": [
				{
					"title": "Kunden",
					"view": "org.mgnl.nicki.consulting.views.CustomersView"
				},
				{
					"title": "Personen",
					"view": "org.mgnl.nicki.consulting.views.PersonsView"
				},
				{
					"title": "Personen LDAP",
					"view": "org.mgnl.nicki.consulting.app.UserEditorComponent"
				},
				{
					"title": "Templates",
					"view": "org.mgnl.nicki.consulting.views.TemplateEditorView"
				},
				{
					"title": "Reports",
					"view": "org.mgnl.nicki.consulting.views.ReportsView",
					"configuration" : {
						"type" : "GROUP_OF_TEMPLATES",
						"path" : "reports/reports"
					}
				}
			]
		},
		{
			"chapter": "Zeiterfassung",
			"views": [
				{
					"title": "Zeiterfassung",
					"view": "org.mgnl.nicki.consulting.views.TimeSheetView"
				},
				{
					"title": "Meine Projekte",
					"view": "org.mgnl.nicki.consulting.views.MyProjectsView"
				}
			]
		},
		{
			"chapter": "Reports",
			"views": [
				{
					"title": "Zeit Report",
					"view": "org.mgnl.nicki.consulting.views.ReportsView",
					"configuration" : {
						"type" : "TEMPLATE",
						"path" : "reports/reports/TimeReport"
					}
				}
			]
		}
	]
}
